[
    {
        "programName": "Enter the Matrix of rows and columns entered by the user and print in matrix format",
        "code": "<span class='colorGreen'>// Enter the Matrix of rows and columns entered by the user and print in matrix format</span>\nimport java.util.Scanner;\n\npublic class program1 {\n\n    public static void main(String[] args) {\n        Scanner scanner = new Scanner(System.in);\n\n        // Input the number of rows and columns from the user\n        System.out.print(\"Enter the number of rows: \");\n        int rows = scanner.nextInt();\n\n        System.out.print(\"Enter the number of columns: \");\n        int columns = scanner.nextInt();\n\n        // Input the matrix elements from the user\n        int[][] matrix = new int[rows][columns];\n        System.out.println(\"Enter the matrix elements:\");\n\n        for (int i = 0; i < rows; i++) {\n            for (int j = 0; j < columns; j++) {\n                System.out.print(\"Enter element at position (\" + (i + 1) + \",\" + (j + 1) + \"): \");\n                matrix[i][j] = scanner.nextInt();\n            }\n        }\n\n        // Print the matrix in matrix format\n        System.out.println(\"Matrix:\");\n\n        for (int i = 0; i < rows; i++) {\n            for (int j = 0; j < columns; j++) {\n                System.out.print(matrix[i][j] + \"\t\");\n            }\n            System.out.println(); // Move to the next line for the next row\n        }\n\n        // Close the scanner\n        scanner.close();\n    }\n}\n\n",
        "output": "Enter the number of rows:  \n3\nEnter the number of columns: 2\nEnter the matrix elements:\nEnter element at position (1,1): 10\nEnter element at position (1,2): 50\nEnter element at position (2,1): 40\nEnter element at position (2,2): 1\nEnter element at position (3,1): 6\nEnter element at position (3,2): 8\nMatrix:\n10      50\n40      1\n6       8\n"
    },
    {
        "programName": "Program to Add Two Matrices",
        "code": "<span class='colorGreen'>// Program to Add Two Matrices</span>\nimport java.util.Scanner;\n\npublic class program2 {\n\n    public static void main(String[] args) {\n        Scanner scanner = new Scanner(System.in);\n\n        // Input the dimensions of the matrices\n        System.out.print(\"Enter the number of rows: \");\n        int rows = scanner.nextInt();\n\n        System.out.print(\"Enter the number of columns: \");\n        int columns = scanner.nextInt();\n\n        // Input the elements of the first matrix\n        System.out.println(\"Enter the elements of the first matrix:\");\n        int[][] matrix1 = inputMatrix(rows, columns, scanner);\n\n        // Input the elements of the second matrix\n        System.out.println(\"Enter the elements of the second matrix:\");\n        int[][] matrix2 = inputMatrix(rows, columns, scanner);\n\n        // Add the matrices and print the result\n        System.out.println(\"Sum of the matrices:\");\n        printMatrix(addMatrices(matrix1, matrix2));\n\n        // Close the scanner\n        scanner.close();\n    }\n\n    public static int[][] inputMatrix(int rows, int columns, Scanner scanner) {\n        int[][] matrix = new int[rows][columns];\n\n        for (int i = 0; i < rows; i++) {\n            for (int j = 0; j < columns; j++) {\n                System.out.print(\"Enter element at position (\" + (i + 1) + \",\" + (j + 1) + \"): \");\n                matrix[i][j] = scanner.nextInt();\n            }\n        }\n\n        return matrix;\n    }\n\n    public static int[][] addMatrices(int[][] matrix1, int[][] matrix2) {\n        int rows = matrix1.length;\n        int columns = matrix1[0].length;\n\n        int[][] sumMatrix = new int[rows][columns];\n\n        for (int i = 0; i < rows; i++) {\n            for (int j = 0; j < columns; j++) {\n                sumMatrix[i][j] = matrix1[i][j] + matrix2[i][j];\n            }\n        }\n\n        return sumMatrix;\n    }\n\n    public static void printMatrix(int[][] matrix) {\n        for (int[] row : matrix) {\n            for (int element : row) {\n                System.out.print(element + \"\t\");\n            }\n            System.out.println(); // Move to the next line for the next row\n        }\n    }\n}\n",
        "output": "Enter the number of rows: 3\nEnter the number of columns: 3\nEnter the elements of the first matrix:\nEnter element at position (1,1): 12\nEnter element at position (1,2): 5\nEnter element at position (1,3): 1\nEnter element at position (2,1): 2\nEnter element at position (2,2): 6\nEnter element at position (2,3): 9\nEnter element at position (3,1): 4\nEnter element at position (3,2): 63\nEnter element at position (3,3): 2\nEnter the elements of the second matrix:\nEnter element at position (1,1): 1\nEnter element at position (1,2): 2\nEnter element at position (1,3): 56\nEnter element at position (2,1): 4\nEnter element at position (2,2): 6\nEnter element at position (2,3): 3\nEnter element at position (3,1): 7\nEnter element at position (3,2): 0\nEnter element at position (3,3): 22\nSum of the matrices:\n13      7       57\n6       12      12\n11      63      24\n"
    },
    {
        "programName": "Program to Multiply Two Matrices",
        "code": "<span class='colorGreen'>// Program to Multiply Two Matrices</span>\nimport java.util.Scanner;\n\npublic class program3 {\n\n    public static void main(String[] args) {\n        Scanner scanner = new Scanner(System.in);\n\n        // Input the dimensions of the first matrix\n        System.out.print(\"Enter the number of rows for the first matrix: \");\n        int rows1 = scanner.nextInt();\n\n        System.out.print(\"Enter the number of columns for the first matrix: \");\n        int columns1 = scanner.nextInt();\n\n        // Input the elements of the first matrix\n        int[][] matrix1 = inputMatrix(rows1, columns1, \"first\", scanner);\n\n        // Input the dimensions of the second matrix\n        System.out.print(\"Enter the number of rows for the second matrix: \");\n        int rows2 = scanner.nextInt();\n\n        System.out.print(\"Enter the number of columns for the second matrix: \");\n        int columns2 = scanner.nextInt();\n\n        // Input the elements of the second matrix\n        int[][] matrix2 = inputMatrix(rows2, columns2, \"second\", scanner);\n\n        // Check if matrices can be multiplied\n        if (columns1 != rows2) {\n            System.out.println(\"Matrices cannot be multiplied. Number of columns in the first matrix must be equal to the number of rows in the second matrix.\");\n        } else {\n            // Multiply the matrices\n            int[][] productMatrix = multiplyMatrices(matrix1, matrix2);\n\n            // Print the result matrix\n            System.out.println(\"Product of the matrices:\");\n            printMatrix(productMatrix);\n        }\n\n        // Close the scanner\n        scanner.close();\n    }\n\n    public static int[][] inputMatrix(int rows, int columns, String ordinal, Scanner scanner) {\n        System.out.println(\"Enter the elements of the \" + ordinal + \" matrix:\");\n\n        int[][] matrix = new int[rows][columns];\n\n        for (int i = 0; i < rows; i++) {\n            for (int j = 0; j < columns; j++) {\n                System.out.print(\"Enter element at position (\" + (i + 1) + \",\" + (j + 1) + \"): \");\n                matrix[i][j] = scanner.nextInt();\n            }\n        }\n\n        return matrix;\n    }\n\n    public static int[][] multiplyMatrices(int[][] matrix1, int[][] matrix2) {\n        int rows1 = matrix1.length;\n        int columns1 = matrix1[0].length;\n        int rows2 = matrix2.length;\n        int columns2 = matrix2[0].length;\n\n        int[][] productMatrix = new int[rows1][columns2];\n\n        for (int i = 0; i < rows1; i++) {\n            for (int j = 0; j < columns2; j++) {\n                for (int k = 0; k < columns1; k++) {\n                    productMatrix[i][j] += matrix1[i][k] * matrix2[k][j];\n                }\n            }\n        }\n\n        return productMatrix;\n    }\n\n    public static void printMatrix(int[][] matrix) {\n        for (int[] row : matrix) {\n            for (int element : row) {\n                System.out.print(element + \"\t\");\n            }\n            System.out.println(); // Move to the next line for the next row\n        }\n    }\n}\n\n",
        "output": "Enter the number of rows for the first matrix: 2\nEnter the number of columns for the first matrix: 2\nEnter the elements of the first matrix:\nEnter element at position (1,1): 6\nEnter element at position (1,2): 5\nEnter element at position (2,1): 3\nEnter element at position (2,2): 1\nEnter the number of rows for the second matrix: 2\nEnter the number of columns for the second matrix: 2\nEnter the elements of the second matrix:\nEnter element at position (1,1): 6\nEnter element at position (1,2): 3\nEnter element at position (2,1): 4\nEnter element at position (2,2): 6\nProduct of the matrices:\n56      48\n22      15"
    },
    {
        "programName": "Program to subtract the two matrices",
        "code": "<span class='colorGreen'>// Program to subtract the two matrices</span>\nimport java.util.Scanner;\n\npublic class program4 {\n\n    public static void main(String[] args) {\n        Scanner scanner = new Scanner(System.in);\n\n        // Input the dimensions of the matrices\n        System.out.print(\"Enter the number of rows: \");\n        int rows = scanner.nextInt();\n\n        System.out.print(\"Enter the number of columns: \");\n        int columns = scanner.nextInt();\n\n        // Input the elements of the first matrix\n        int[][] matrix1 = inputMatrix(\"first\", rows, columns, scanner);\n\n        // Input the elements of the second matrix\n        int[][] matrix2 = inputMatrix(\"second\", rows, columns, scanner);\n\n        // Subtract the matrices\n        int[][] differenceMatrix = subtractMatrices(matrix1, matrix2);\n\n        // Print the result matrix\n        System.out.println(\"Difference of the matrices:\");\n        printMatrix(differenceMatrix);\n\n        // Close the scanner\n        scanner.close();\n    }\n\n    public static int[][] inputMatrix(String ordinal, int rows, int columns, Scanner scanner) {\n        System.out.println(\"Enter the elements of the \" + ordinal + \" matrix:\");\n\n        int[][] matrix = new int[rows][columns];\n\n        for (int i = 0; i < rows; i++) {\n            for (int j = 0; j < columns; j++) {\n                System.out.print(\"Enter element at position (\" + (i + 1) + \",\" + (j + 1) + \"): \");\n                matrix[i][j] = scanner.nextInt();\n            }\n        }\n\n        return matrix;\n    }\n\n    public static int[][] subtractMatrices(int[][] matrix1, int[][] matrix2) {\n        int rows = matrix1.length;\n        int columns = matrix1[0].length;\n\n        int[][] differenceMatrix = new int[rows][columns];\n\n        for (int i = 0; i < rows; i++) {\n            for (int j = 0; j < columns; j++) {\n                differenceMatrix[i][j] = matrix1[i][j] - matrix2[i][j];\n            }\n        }\n\n        return differenceMatrix;\n    }\n\n    public static void printMatrix(int[][] matrix) {\n        for (int[] row : matrix) {\n            for (int element : row) {\n                System.out.print(element + \"\t\");\n            }\n            System.out.println(); // Move to the next line for the next row\n        }\n    }\n}\n",
        "output": "Enter the number of rows: 2\n        Enter the number of columns: 2\n        Enter the elements of the first matrix:\n        Enter element at position (1,1): 5\n        Enter element at position (1,2): 6\n        Enter element at position (2,1): 3\n        Enter element at position (2,2): 4\n        Enter the elements of the second matrix:\n        Enter element at position (1,1): 2\n        Enter element at position (1,2): 6\n        Enter element at position (2,1): 4\n        Enter element at position (2,2): 8\n        Difference of the matrices:\n        3       0\n        -1      -4"
    },
    {
        "programName": "Program to determine whether two matrices are equal",
        "code": "<span class='colorGreen'>// Program to determine whether two matrices are equal</span>\nimport java.util.Scanner;\n\npublic class program5 {\n\n    public static void main(String[] args) {\n        Scanner scanner = new Scanner(System.in);\n\n        // Input the dimensions of the matrices\n        System.out.print(\"Enter the number of rows: \");\n        int rows = scanner.nextInt();\n\n        System.out.print(\"Enter the number of columns: \");\n        int columns = scanner.nextInt();\n\n        // Input the elements of the first matrix\n        int[][] matrix1 = inputMatrix(\"first\", rows, columns, scanner);\n\n        // Input the elements of the second matrix\n        int[][] matrix2 = inputMatrix(\"second\", rows, columns, scanner);\n\n        // Check if the matrices are equal\n        boolean areEqual = areMatricesEqual(matrix1, matrix2);\n\n        // Print the result\n        if (areEqual) {\n            System.out.println(\"The matrices are equal.\");\n        } else {\n            System.out.println(\"The matrices are not equal.\");\n        }\n\n        // Close the scanner\n        scanner.close();\n    }\n\n    public static int[][] inputMatrix(String ordinal, int rows, int columns, Scanner scanner) {\n        System.out.println(\"Enter the elements of the \" + ordinal + \" matrix:\");\n\n        int[][] matrix = new int[rows][columns];\n\n        for (int i = 0; i < rows; i++) {\n            for (int j = 0; j < columns; j++) {\n                System.out.print(\"Enter element at position (\" + (i + 1) + \",\" + (j + 1) + \"): \");\n                matrix[i][j] = scanner.nextInt();\n            }\n        }\n\n        return matrix;\n    }\n\n    public static boolean areMatricesEqual(int[][] matrix1, int[][] matrix2) {\n        int rows = matrix1.length;\n        int columns = matrix1[0].length;\n\n        if (matrix2.length != rows || matrix2[0].length != columns) {\n            return false; // Matrices have different dimensions\n        }\n\n        for (int i = 0; i < rows; i++) {\n            for (int j = 0; j < columns; j++) {\n                if (matrix1[i][j] != matrix2[i][j]) {\n                    return false; // Matrices have different elements\n                }\n            }\n        }\n\n        return true; // Matrices are equal\n    }\n}\n",
        "output": "Enter the number of rows: 2\nEnter the number of columns: 2\nEnter the elements of the first matrix:\nEnter element at position (1,1): 6\nEnter element at position (1,2): \n56\nEnter element at position (2,1): 3\nEnter element at position (2,2): 4\nEnter the elements of the second matrix:\nEnter element at position (1,1): 2\nEnter element at position (1,2): 5\nEnter element at position (2,1): 8\nEnter element at position (2,2): 1\nThe matrices are not equal.\n"
    },
    {
        "programName": "Program to display the lower triangular matrix",
        "code": "<span class='colorGreen'>// Program to display the lower triangular matrix</span>\nimport java.util.Scanner;\n\npublic class program6 {\n\n    public static void main(String[] args) {\n        Scanner scanner = new Scanner(System.in);\n\n        // Input the size of the square matrix\n        System.out.print(\"Enter the size of the square matrix: \");\n        int size = scanner.nextInt();\n\n        // Input the elements of the square matrix\n        int[][] matrix = inputSquareMatrix(size, scanner);\n\n        // Display the lower triangular matrix\n        System.out.println(\"Lower Triangular Matrix:\");\n        displayLowerTriangularMatrix(matrix);\n\n        // Close the scanner\n        scanner.close();\n    }\n\n    public static int[][] inputSquareMatrix(int size, Scanner scanner) {\n        System.out.println(\"Enter the elements of the square matrix:\");\n\n        int[][] matrix = new int[size][size];\n\n        for (int i = 0; i < size; i++) {\n            for (int j = 0; j < size; j++) {\n                System.out.print(\"Enter element at position (\" + (i + 1) + \",\" + (j + 1) + \"): \");\n                matrix[i][j] = scanner.nextInt();\n            }\n        }\n\n        return matrix;\n    }\n\n    public static void displayLowerTriangularMatrix(int[][] matrix) {\n        int size = matrix.length;\n\n        for (int i = 0; i < size; i++) {\n            for (int j = 0; j < size; j++) {\n                if (j <= i) {\n                    System.out.print(matrix[i][j] + \"\t\");\n                } else {\n                    System.out.print(\"0\t\"); // Print 0 for elements above the main diagonal\n                }\n            }\n            System.out.println(); // Move to the next line for the next row\n        }\n    }\n}\n",
        "output": "Enter the size of the square matrix: 3\nEnter the elements of the square matrix:\nEnter element at position (1,1): 2\nEnter element at position (1,2): 5\nEnter element at position (1,3): 6\nEnter element at position (2,1): 8\nEnter element at position (2,2): 4\nEnter element at position (2,3): 2\nEnter element at position (3,1): 0\nEnter element at position (3,2): 4\nEnter element at position (3,3): 5\nLower Triangular Matrix:\n2       0       0\n8       4       0\n0       4       5\n"
    },
    {
        "programName": "Program to display the upper triangular matrix",
        "code": "<span class='colorGreen'>// Program to display the upper triangular matrix</span>\nimport java.util.Scanner;\n\npublic class UpperTriangularMatrix {\n\n    public static void main(String[] args) {\n        Scanner scanner = new Scanner(System.in);\n\n        // Input the size of the square matrix\n        System.out.print(\"Enter the size of the square matrix: \");\n        int size = scanner.nextInt();\n\n        // Input the elements of the square matrix\n        int[][] matrix = inputSquareMatrix(size, scanner);\n\n        // Display the upper triangular matrix\n        System.out.println(\"Upper Triangular Matrix:\");\n        displayUpperTriangularMatrix(matrix);\n\n        // Close the scanner\n        scanner.close();\n    }\n\n    public static int[][] inputSquareMatrix(int size, Scanner scanner) {\n        System.out.println(\"Enter the elements of the square matrix:\");\n\n        int[][] matrix = new int[size][size];\n\n        for (int i = 0; i < size; i++) {\n            for (int j = 0; j < size; j++) {\n                System.out.print(\"Enter element at position (\" + (i + 1) + \",\" + (j + 1) + \"): \");\n                matrix[i][j] = scanner.nextInt();\n            }\n        }\n\n        return matrix;\n    }\n\n    public static void displayUpperTriangularMatrix(int[][] matrix) {\n        int size = matrix.length;\n\n        for (int i = 0; i < size; i++) {\n            for (int j = 0; j < size; j++) {\n                if (j >= i) {\n                    System.out.print(matrix[i][j] + \"\t\");\n                } else {\n                    System.out.print(\"0\t\"); // Print 0 for elements below the main diagonal\n                }\n            }\n            System.out.println(); // Move to the next line for the next row\n        }\n    }\n}\n",
        "output": "Enter the size of the square matrix: 4\nEnter the elements of the square matrix:\nEnter element at position (1,1): 2\nEnter element at position (1,2): 6\nEnter element at position (1,3): 5\nEnter element at position (1,4): 3\nEnter element at position (2,1): 4\nEnter element at position (2,2): 1\nEnter element at position (2,3): 2\nEnter element at position (2,4): 3\nEnter element at position (3,1): 5\nEnter element at position (3,2): 6\nEnter element at position (3,3): 77\nEnter element at position (3,4): 8\nEnter element at position (4,1): 10\nEnter element at position (4,2): 25\nEnter element at position (4,3): 3\nEnter element at position (4,4): 5\nUpper Triangular Matrix:\n2       6       5       3\n0       1       2       3\n0       0       77      8\n0       0       0       5\n"
    },
    {
        "programName": "Program to find the frequency of odd & even numbers in the given matrix",
        "code": "<span class='colorGreen'>// Program to find the frequency of odd & even numbers in the given matrix</span>\nimport java.util.Scanner;\n\npublic class program8 {\n\n    public static void main(String[] args) {\n        Scanner scanner = new Scanner(System.in);\n\n        // Input the size of the matrix\n        System.out.print(\"Enter the number of rows: \");\n        int rows = scanner.nextInt();\n\n        System.out.print(\"Enter the number of columns: \");\n        int columns = scanner.nextInt();\n\n        // Input the elements of the matrix\n        int[][] matrix = inputMatrix(rows, columns, scanner);\n\n        // Calculate and display the frequency of odd and even numbers\n        int oddFrequency = 0;\n        int evenFrequency = 0;\n\n        for (int i = 0; i < rows; i++) {\n            for (int j = 0; j < columns; j++) {\n                if (matrix[i][j] % 2 == 0) {\n                    evenFrequency++;\n                } else {\n                    oddFrequency++;\n                }\n            }\n        }\n\n        System.out.println(\"Frequency of odd numbers: \" + oddFrequency);\n        System.out.println(\"Frequency of even numbers: \" + evenFrequency);\n\n        // Close the scanner\n        scanner.close();\n    }\n\n    public static int[][] inputMatrix(int rows, int columns, Scanner scanner) {\n        System.out.println(\"Enter the elements of the matrix:\");\n\n        int[][] matrix = new int[rows][columns];\n\n        for (int i = 0; i < rows; i++) {\n            for (int j = 0; j < columns; j++) {\n                System.out.print(\"Enter element at position (\" + (i + 1) + \",\" + (j + 1) + \"): \");\n                matrix[i][j] = scanner.nextInt();\n            }\n        }\n\n        return matrix;\n    }\n}\n",
        "output": "Enter the number of rows: 2\n        Enter the number of columns: 3\n        Enter the elements of the matrix:\n        Enter element at position (1,1): 15\n        Enter element at position (1,2): 2\n        Enter element at position (1,3): 6\n        Enter element at position (2,1): 48\n        Enter element at position (2,2): 30\n        Enter element at position (2,3): 12\n        Frequency of odd numbers: 1\n        Frequency of even numbers: 5"
    },
    {
        "programName": "Program to find the sum of each row and each column of a matrix",
        "code": "<span class='colorGreen'>// Program to find the sum of each row and each column of a matrix</span>\nimport java.util.Scanner;\n\npublic class program9 {\n\n    public static void main(String[] args) {\n        Scanner scanner = new Scanner(System.in);\n\n        // Input the size of the matrix\n        System.out.print(\"Enter the number of rows: \");\n        int rows = scanner.nextInt();\n\n        System.out.print(\"Enter the number of columns: \");\n        int columns = scanner.nextInt();\n\n        // Input the elements of the matrix\n        int[][] matrix = inputMatrix(rows, columns, scanner);\n\n        // Calculate and display the sum of each row\n        System.out.println(\"Sum of each row:\");\n\n        for (int i = 0; i < rows; i++) {\n            int rowSum = 0;\n            for (int j = 0; j < columns; j++) {\n                rowSum += matrix[i][j];\n            }\n            System.out.println(\"Row \" + (i + 1) + \": \" + rowSum);\n        }\n\n        // Calculate and display the sum of each column\n        System.out.println(\"Sum of each column:\");\n\n        for (int j = 0; j < columns; j++) {\n            int columnSum = 0;\n            for (int i = 0; i < rows; i++) {\n                columnSum += matrix[i][j];\n            }\n            System.out.println(\"Column \" + (j + 1) + \": \" + columnSum);\n        }\n\n        // Close the scanner\n        scanner.close();\n    }\n\n    public static int[][] inputMatrix(int rows, int columns, Scanner scanner) {\n        System.out.println(\"Enter the elements of the matrix:\");\n\n        int[][] matrix = new int[rows][columns];\n\n        for (int i = 0; i < rows; i++) {\n            for (int j = 0; j < columns; j++) {\n                System.out.print(\"Enter element at position (\" + (i + 1) + \",\" + (j + 1) + \"): \");\n                matrix[i][j] = scanner.nextInt();\n            }\n        }\n\n        return matrix;\n    }\n}\n",
        "output": "Enter the number of rows: 2\nEnter the number of columns: 3\nEnter the elements of the matrix:\nEnter element at position (1,1): 5\nEnter element at position (1,2): 6\nEnter element at position (1,3): 42\nEnter element at position (2,1): 01\nEnter element at position (2,2): 23\nEnter element at position (2,3): 6\nSum of each row:\nRow 1: 53\nRow 2: 30\nSum of each column:\nColumn 1: 6\nColumn 2: 29\nColumn 3: 48"
    },
    {
        "programName": "Program to find the transpose of a given matrix",
        "code": "<span class='colorGreen'>// Program to find the transpose of a given matrix</span>\npublic class program10 {\n\n    public static void main(String[] args) {\n        // Assume a 3x3 matrix for demonstration\n        int[][] matrix = {\n                {1, 2, 3},\n                {4, 5, 6},\n                {7, 8, 9}\n        };\n\n        // Print the original matrix\n        System.out.println(\"Original Matrix:\");\n        printMatrix(matrix);\n\n        // Calculate and display the transpose of the matrix\n        int[][] transposeMatrix = transpose(matrix);\n\n        System.out.println(\"Transpose Matrix:\");\n        printMatrix(transposeMatrix);\n    }\n\n    public static int[][] transpose(int[][] matrix) {\n        int rows = matrix.length;\n        int columns = matrix[0].length;\n\n        int[][] transposeMatrix = new int[columns][rows];\n\n        for (int i = 0; i < rows; i++) {\n            for (int j = 0; j < columns; j++) {\n                transposeMatrix[j][i] = matrix[i][j];\n            }\n        }\n\n        return transposeMatrix;\n    }\n\n    public static void printMatrix(int[][] matrix) {\n        for (int[] row : matrix) {\n            for (int element : row) {\n                System.out.print(element + \"\t\");\n            }\n            System.out.println(); // Move to the next line for the next row\n        }\n    }\n}\n",
        "output": "Original Matrix:\n1       2       3\n4       5       6\n7       8       9\nTranspose Matrix:\n1       4       7\n2       5       8\n3       6       9\n"
    },
    {
        "programName": "Program to determine whether a given matrix is an identity matrix",
        "code": "<span class='colorGreen'>// Program to determine whether a given matrix is an identity matrix</span>\npublic class IdentityMatrixChecker {\n    public static void main(String[] args) {\n        int[][] matrix = {\n            {1, 0, 0},\n            {0, 1, 0},\n            {0, 0, 1}\n        };\n\n        if (isIdentityMatrix(matrix)) {\n            System.out.println(\"The matrix is an identity matrix.\");\n        } else {\n            System.out.println(\"The matrix is not an identity matrix.\");\n        }\n    }\n\n    public static boolean isIdentityMatrix(int[][] matrix) {\n        int rows = matrix.length;\n        int cols = (rows > 0) ? matrix[0].length : 0;\n\n        // Check if the matrix is square\n        if (rows != cols) {\n            return false;\n        }\n\n        // Check diagonal elements\n        for (int i = 0; i < rows; i++) {\n            for (int j = 0; j < cols; j++) {\n                if (i == j && matrix[i][j] != 1) {\n                    return false;\n                } else if (i != j && matrix[i][j] != 0) {\n                    return false;\n                }\n            }\n        }\n\n        // If all conditions are satisfied, the matrix is an identity matrix\n        return true;\n    }\n}\n\n",
        "output": "The matrix is an identity matrix."
    },
    {
        "programName": "Program to determine whether a given matrix is a sparse matrix",
        "code": "<span class='colorGreen'>// Program to determine whether a given matrix is a sparse matrix</span>\npublic class program13 {\n\n    public static void main(String[] args) {\n        // Assume a 3x3 matrix for demonstration\n        int[][] matrix = {\n                {1, 0, 0},\n                {0, 0, 0},\n                {0, 0, 2}\n        };\n\n        // Print the matrix\n        System.out.println(\"Given Matrix:\");\n        printMatrix(matrix);\n\n        // Check if the matrix is a sparse matrix\n        boolean isSparse = isSparseMatrix(matrix);\n\n        // Print the result\n        if (isSparse) {\n            System.out.println(\"The given matrix is a sparse matrix.\");\n        } else {\n            System.out.println(\"The given matrix is not a sparse matrix.\");\n        }\n    }\n\n    public static boolean isSparseMatrix(int[][] matrix) {\n        int rows = matrix.length;\n        int columns = matrix[0].length;\n\n        int zeroCount = 0;\n        int nonZeroCount = 0;\n\n        // Count the number of zeros and non-zeros\n        for (int i = 0; i < rows; i++) {\n            for (int j = 0; j < columns; j++) {\n                if (matrix[i][j] == 0) {\n                    zeroCount++;\n                } else {\n                    nonZeroCount++;\n                }\n            }\n        }\n\n        // Check if the matrix is sparse based on the number of zeros\n        return zeroCount > nonZeroCount;\n    }\n\n    public static void printMatrix(int[][] matrix) {\n        for (int[] row : matrix) {\n            for (int element : row) {\n                System.out.print(element + \"\t\");\n            }\n            System.out.println(); // Move to the next line for the next row\n        }\n    }\n}\n",
        "output": "Given Matrix:\n1       0       0\n0       0       0\n0       0       2\nThe given matrix is a sparse matrix.\n"
    }
]